uutel/__init__.py
uutel/__main__.py
uutel/_version.py
uutel/uutel.py
uutel/core/__init__.py
uutel/core/auth.py
uutel/core/base.py
uutel/core/config.py
uutel/core/exceptions.py
uutel/core/fixture_validation.py
uutel/core/logging_config.py
uutel/core/runners.py
uutel/core/utils.py
uutel/providers/__init__.py
uutel/providers/claude_code/__init__.py
uutel/providers/claude_code/provider.py
uutel/providers/cloud_code/__init__.py
uutel/providers/cloud_code/provider.py
uutel/providers/codex/__init__.py
uutel/providers/codex/custom_llm.py
uutel/providers/codex/provider.py
uutel/providers/gemini_cli/__init__.py
uutel/providers/gemini_cli/provider.py
uutel-1.0.10.dist-info/METADATA
uutel-1.0.10.dist-info/WHEEL
uutel-1.0.10.dist-info/entry_points.txt
uutel-1.0.10.dist-info/licenses/LICENSE
uutel-1.0.10.dist-info/RECORD
