Metadata-Version: 2.4
Name: uutel
Version: 1.0.10
Summary: Universal AI Provider for LiteLLM with CLI interface - extends LiteLLM with Claude Code, Gemini CLI, Google Cloud Code, and OpenAI Codex providers for unified LLM inferencing and command-line completions
Project-URL: Homepage, https://github.com/twardoch/uutel
Project-URL: Documentation, https://github.com/twardoch/uutel#readme
Project-URL: Repository, https://github.com/twardoch/uutel
Project-URL: Source, https://github.com/twardoch/uutel
Project-URL: Bug Tracker, https://github.com/twardoch/uutel/issues
Project-URL: Issues, https://github.com/twardoch/uutel/issues
Project-URL: Changelog, https://github.com/twardoch/uutel/blob/main/CHANGELOG.md
Project-URL: Development Guide, https://github.com/twardoch/uutel/blob/main/DEVELOPMENT.md
Project-URL: Contributing, https://github.com/twardoch/uutel/blob/main/CONTRIBUTING.md
Author-email: Adam Twardoch <adam+github@twardoch.com>
Maintainer-email: Adam Twardoch <adam+github@twardoch.com>
License: MIT
License-File: LICENSE
Keywords: ai,ai-cli,anthropic,api,artificial-intelligence,chat,chatgpt,claude,cli,cloud-code,codex,command-line,completion,completion-tool,console,conversational-ai,engine,fire,function-calling,gemini,google,gpt,inference,litellm,llm,machine-learning,mcp,nlp,oauth,openai,prompt,providers,sdk,single-turn,streaming,terminal,tool-calling,universal,vertex-ai
Classifier: Development Status :: 4 - Beta
Classifier: Environment :: Console
Classifier: Environment :: Web Environment
Classifier: Framework :: AsyncIO
Classifier: Intended Audience :: Developers
Classifier: Intended Audience :: Information Technology
Classifier: Intended Audience :: Science/Research
Classifier: Intended Audience :: System Administrators
Classifier: License :: OSI Approved :: MIT License
Classifier: Natural Language :: English
Classifier: Operating System :: OS Independent
Classifier: Programming Language :: Python
Classifier: Programming Language :: Python :: 3.10
Classifier: Programming Language :: Python :: 3.11
Classifier: Programming Language :: Python :: 3.12
Classifier: Programming Language :: Python :: Implementation :: CPython
Classifier: Topic :: Communications :: Chat
Classifier: Topic :: Internet :: WWW/HTTP :: Dynamic Content
Classifier: Topic :: Scientific/Engineering :: Artificial Intelligence
Classifier: Topic :: Software Development :: Libraries :: Application Frameworks
Classifier: Topic :: Software Development :: Libraries :: Python Modules
Classifier: Topic :: System :: Shells
Classifier: Topic :: Terminals
Classifier: Topic :: Text Processing :: Linguistic
Classifier: Topic :: Utilities
Classifier: Typing :: Typed
Requires-Python: >=3.10
Requires-Dist: aiohttp>=3.9.0
Requires-Dist: fire>=0.7.1
Requires-Dist: httpx[http2]>=0.27.0
Requires-Dist: litellm>=1.74.0
Requires-Dist: loguru>=0.7.2
Requires-Dist: psutil>=5.9.0
Requires-Dist: pydantic-settings>=2.4.0
Requires-Dist: pydantic>=2.8.0
Requires-Dist: tomli-w>=1.0.0
Requires-Dist: tomli>=1.2.0; python_version < '3.11'
Provides-Extra: all
Requires-Dist: browser-cookie3>=0.19.1; extra == 'all'
Requires-Dist: click>=8.1.0; extra == 'all'
Requires-Dist: google-api-python-client>=2.130.0; extra == 'all'
Requires-Dist: google-auth-oauthlib>=1.2.0; extra == 'all'
Requires-Dist: google-auth>=2.29.0; extra == 'all'
Requires-Dist: google-cloud-aiplatform>=1.55.0; extra == 'all'
Requires-Dist: google-cloud-core>=2.4.1; extra == 'all'
Requires-Dist: google-cloud-resource-manager>=1.12.3; extra == 'all'
Requires-Dist: google-generativeai>=0.7.0; extra == 'all'
Requires-Dist: keyring>=24.3.1; extra == 'all'
Requires-Dist: mkdocs-gen-files>=0.5.0; extra == 'all'
Requires-Dist: mkdocs-material>=9.5.0; extra == 'all'
Requires-Dist: mkdocs>=1.6.0; extra == 'all'
Requires-Dist: mkdocstrings[python]>=0.25.0; extra == 'all'
Requires-Dist: openai>=1.35.0; extra == 'all'
Requires-Dist: requests>=2.31.0; extra == 'all'
Requires-Dist: rich>=13.7.0; extra == 'all'
Requires-Dist: selenium>=4.18.0; extra == 'all'
Requires-Dist: tiktoken>=0.7.0; extra == 'all'
Requires-Dist: typer>=0.12.0; extra == 'all'
Provides-Extra: auth
Requires-Dist: browser-cookie3>=0.19.1; extra == 'auth'
Requires-Dist: google-auth-oauthlib>=1.2.0; extra == 'auth'
Requires-Dist: google-auth>=2.29.0; extra == 'auth'
Requires-Dist: google-cloud-core>=2.4.1; extra == 'auth'
Requires-Dist: keyring>=24.3.1; extra == 'auth'
Provides-Extra: claude-code
Requires-Dist: browser-cookie3>=0.19.1; extra == 'claude-code'
Requires-Dist: requests>=2.31.0; extra == 'claude-code'
Requires-Dist: selenium>=4.18.0; extra == 'claude-code'
Provides-Extra: cli
Requires-Dist: click>=8.1.0; extra == 'cli'
Requires-Dist: rich>=13.7.0; extra == 'cli'
Requires-Dist: typer>=0.12.0; extra == 'cli'
Provides-Extra: cloud-code
Requires-Dist: google-api-python-client>=2.130.0; extra == 'cloud-code'
Requires-Dist: google-auth>=2.29.0; extra == 'cloud-code'
Requires-Dist: google-cloud-core>=2.4.1; extra == 'cloud-code'
Requires-Dist: google-cloud-resource-manager>=1.12.3; extra == 'cloud-code'
Provides-Extra: codex
Requires-Dist: keyring>=24.3.1; extra == 'codex'
Requires-Dist: openai>=1.35.0; extra == 'codex'
Requires-Dist: tiktoken>=0.7.0; extra == 'codex'
Provides-Extra: dev
Requires-Dist: bandit[toml]>=1.7.5; extra == 'dev'
Requires-Dist: mypy>=1.10.0; extra == 'dev'
Requires-Dist: pre-commit>=3.7.0; extra == 'dev'
Requires-Dist: ruff>=0.5.0; extra == 'dev'
Requires-Dist: safety>=3.2.0; extra == 'dev'
Requires-Dist: uv>=0.2.0; extra == 'dev'
Provides-Extra: docs
Requires-Dist: mkdocs-gen-files>=0.5.0; extra == 'docs'
Requires-Dist: mkdocs-material>=9.5.0; extra == 'docs'
Requires-Dist: mkdocs>=1.6.0; extra == 'docs'
Requires-Dist: mkdocstrings[python]>=0.25.0; extra == 'docs'
Provides-Extra: full
Requires-Dist: bandit[toml]>=1.7.5; extra == 'full'
Requires-Dist: browser-cookie3>=0.19.1; extra == 'full'
Requires-Dist: click>=8.1.0; extra == 'full'
Requires-Dist: coverage[toml]>=7.5.0; extra == 'full'
Requires-Dist: google-api-python-client>=2.130.0; extra == 'full'
Requires-Dist: google-auth-oauthlib>=1.2.0; extra == 'full'
Requires-Dist: google-auth>=2.29.0; extra == 'full'
Requires-Dist: google-cloud-aiplatform>=1.55.0; extra == 'full'
Requires-Dist: google-cloud-core>=2.4.1; extra == 'full'
Requires-Dist: google-cloud-resource-manager>=1.12.3; extra == 'full'
Requires-Dist: google-generativeai>=0.7.0; extra == 'full'
Requires-Dist: httpx[socks]>=0.27.0; extra == 'full'
Requires-Dist: keyring>=24.3.1; extra == 'full'
Requires-Dist: line-profiler>=4.1.0; extra == 'full'
Requires-Dist: memory-profiler>=0.61.0; extra == 'full'
Requires-Dist: mkdocs-gen-files>=0.5.0; extra == 'full'
Requires-Dist: mkdocs-material>=9.5.0; extra == 'full'
Requires-Dist: mkdocs>=1.6.0; extra == 'full'
Requires-Dist: mkdocstrings[python]>=0.25.0; extra == 'full'
Requires-Dist: mypy>=1.10.0; extra == 'full'
Requires-Dist: openai>=1.35.0; extra == 'full'
Requires-Dist: pre-commit>=3.7.0; extra == 'full'
Requires-Dist: psutil>=5.9.0; extra == 'full'
Requires-Dist: py-spy>=0.3.0; extra == 'full'
Requires-Dist: pytest-asyncio>=0.23.0; extra == 'full'
Requires-Dist: pytest-cov>=5.0.0; extra == 'full'
Requires-Dist: pytest-mock>=3.14.0; extra == 'full'
Requires-Dist: pytest-xdist>=3.6.0; extra == 'full'
Requires-Dist: pytest>=8.2.0; extra == 'full'
Requires-Dist: requests>=2.31.0; extra == 'full'
Requires-Dist: rich>=13.7.0; extra == 'full'
Requires-Dist: ruff>=0.5.0; extra == 'full'
Requires-Dist: safety>=3.2.0; extra == 'full'
Requires-Dist: selenium>=4.18.0; extra == 'full'
Requires-Dist: tiktoken>=0.7.0; extra == 'full'
Requires-Dist: typer>=0.12.0; extra == 'full'
Requires-Dist: uv>=0.2.0; extra == 'full'
Provides-Extra: gemini-cli
Requires-Dist: google-api-python-client>=2.130.0; extra == 'gemini-cli'
Requires-Dist: google-auth-oauthlib>=1.2.0; extra == 'gemini-cli'
Requires-Dist: google-auth>=2.29.0; extra == 'gemini-cli'
Requires-Dist: google-cloud-aiplatform>=1.55.0; extra == 'gemini-cli'
Requires-Dist: google-generativeai>=0.7.0; extra == 'gemini-cli'
Provides-Extra: profile
Requires-Dist: line-profiler>=4.1.0; extra == 'profile'
Requires-Dist: memory-profiler>=0.61.0; extra == 'profile'
Requires-Dist: py-spy>=0.3.0; extra == 'profile'
Provides-Extra: providers
Requires-Dist: browser-cookie3>=0.19.1; extra == 'providers'
Requires-Dist: google-api-python-client>=2.130.0; extra == 'providers'
Requires-Dist: google-auth-oauthlib>=1.2.0; extra == 'providers'
Requires-Dist: google-auth>=2.29.0; extra == 'providers'
Requires-Dist: google-cloud-aiplatform>=1.55.0; extra == 'providers'
Requires-Dist: google-cloud-core>=2.4.1; extra == 'providers'
Requires-Dist: google-cloud-resource-manager>=1.12.3; extra == 'providers'
Requires-Dist: google-generativeai>=0.7.0; extra == 'providers'
Requires-Dist: keyring>=24.3.1; extra == 'providers'
Requires-Dist: openai>=1.35.0; extra == 'providers'
Requires-Dist: requests>=2.31.0; extra == 'providers'
Requires-Dist: selenium>=4.18.0; extra == 'providers'
Requires-Dist: tiktoken>=0.7.0; extra == 'providers'
Provides-Extra: test
Requires-Dist: coverage[toml]>=7.5.0; extra == 'test'
Requires-Dist: httpx[socks]>=0.27.0; extra == 'test'
Requires-Dist: psutil>=5.9.0; extra == 'test'
Requires-Dist: pytest-asyncio>=0.23.0; extra == 'test'
Requires-Dist: pytest-cov>=5.0.0; extra == 'test'
Requires-Dist: pytest-mock>=3.14.0; extra == 'test'
Requires-Dist: pytest-xdist>=3.6.0; extra == 'test'
Requires-Dist: pytest>=8.2.0; extra == 'test'
